ShopifyTupperware/__init__.py
ShopifyTupperware/helper.py
ShopifyTupperware/views.py
ShopifyTupperware/bloc/__init__.py
ShopifyTupperware/bloc/address_bloc.py
ShopifyTupperware/bloc/collection_bloc.py
ShopifyTupperware/bloc/customer_bloc.py
ShopifyTupperware/bloc/discount_bloc.py
ShopifyTupperware/bloc/fulfillment_bloc.py
ShopifyTupperware/bloc/line_item_bloc.py
ShopifyTupperware/bloc/location_bloc.py
ShopifyTupperware/bloc/new_recruit_bloc.py
ShopifyTupperware/bloc/new_waranty_bloc.py
ShopifyTupperware/bloc/order_bloc.py
ShopifyTupperware/bloc/price_rule_bloc.py
ShopifyTupperware/bloc/product_bloc.py
ShopifyTupperware/bloc/recruit_bloc.py
ShopifyTupperware/bloc/shipping_bloc.py
ShopifyTupperware/bloc/transaction_bloc.py
ShopifyTupperware/bloc/waranty_bloc.py
ShopifyTupperware/controllers/__init__.py
ShopifyTupperware/controllers/area_controller.py
ShopifyTupperware/controllers/customer_controller.py
ShopifyTupperware/controllers/discount_controller.py
ShopifyTupperware/controllers/inventory_controller.py
ShopifyTupperware/controllers/location_controller.py
ShopifyTupperware/controllers/order_controller.py
ShopifyTupperware/controllers/product_claim_controller.py
ShopifyTupperware/controllers/product_controller.py
ShopifyTupperware/controllers/recruit_controller.py
ShopifyTupperware/controllers/transaction_controller.py
ShopifyTupperware/controllers/user_controller.py
ShopifyTupperware/controllers/voucher_controller.py
ShopifyTupperware/controllers/waranty_controller.py
ShopifyTupperware/data/__init__.py
ShopifyTupperware/data/address_db.py
ShopifyTupperware/data/area_db.py
ShopifyTupperware/data/collection_db.py
ShopifyTupperware/data/customer2_db.py
ShopifyTupperware/data/customer_db.py
ShopifyTupperware/data/db.py
ShopifyTupperware/data/demo_db.py
ShopifyTupperware/data/discount_allocation_db.py
ShopifyTupperware/data/discount_app_db.py
ShopifyTupperware/data/discount_code_db.py
ShopifyTupperware/data/fulfillment_db.py
ShopifyTupperware/data/gift_db.py
Flask_Shopify_Integration-0.7.dist-info/METADATA
Flask_Shopify_Integration-0.7.dist-info/WHEEL
Flask_Shopify_Integration-0.7.dist-info/top_level.txt
Flask_Shopify_Integration-0.7.dist-info/RECORD
