Metadata-Version: 2.1
Name: Flask-Shopify-Integration
Version: 0.7
Summary: UNKNOWN
Home-page: UNKNOWN
Author: UNKNOWN
Author-email: UNKNOWN
License: UNKNOWN
Platform: 
Requires-Dist: Flask (==2.0.3)
Requires-Dist: Flask-Cors (==3.0.8)
Requires-Dist: Flask-JWT-Extended (==4.4.2)
Requires-Dist: Flask-JWT-Simple (==0.0.3)
Requires-Dist: flask-marshmallow (==0.10.1)
Requires-Dist: Flask-SQLAlchemy (==2.4.1)
Requires-Dist: flask-swagger-ui (==3.36.0)
Requires-Dist: Jinja2 (==3.0.3)
Requires-Dist: MarkupSafe (==2.0.1)
Requires-Dist: marshmallow (==3.3.0)
Requires-Dist: marshmallow-sqlalchemy (==0.21.0)
Requires-Dist: Pillow (==7.2.0)
Requires-Dist: PyJWT (==2.4.0)
Requires-Dist: pyodbc (==4.0.27)
Requires-Dist: python-dotenv (==0.10.3)
Requires-Dist: PyYAML (==5.3)
Requires-Dist: ShopifyAPI (==12.4.0)
Requires-Dist: SQLAlchemy (==1.3.13)
